collective.classifiers-1.0.0b2-py3.9-nspkg.pth
collective/classifiers/__init__.py
collective/classifiers/behaviors.py
collective/classifiers/configure.zcml
collective/classifiers/indexers.py
collective/classifiers/migration.py
collective/classifiers/testing.py
collective/classifiers/update_locales.sh
collective/classifiers/utils.py
collective/classifiers/vocabularies.py
collective/classifiers/locales/collective.classifiers.pot
collective/classifiers/locales/manual.pot
collective/classifiers/locales/plone.pot
collective/classifiers/locales/nl/LC_MESSAGES/collective.classifiers.po
collective/classifiers/locales/nl/LC_MESSAGES/plone.po
collective/classifiers/profiles/default/catalog.xml
collective/classifiers/profiles/default/controlpanel.xml
collective/classifiers/profiles/default/metadata.xml
collective/classifiers/profiles/default/registry.xml
collective/classifiers/profiles/testfixture/metadata.xml
collective/classifiers/profiles/testfixture/registry.xml
collective/classifiers/profiles/testfixture/types.xml
collective/classifiers/profiles/testfixture/types/TestContainer.xml
collective/classifiers/profiles/testfixture/types/TestItem.xml
collective/classifiers/tests/__init__.py
collective/classifiers/tests/test_integration.py
collective/classifiers/tests/test_unit.py
collective.classifiers-1.0.0b2.dist-info/METADATA
collective.classifiers-1.0.0b2.dist-info/WHEEL
collective.classifiers-1.0.0b2.dist-info/entry_points.txt
collective.classifiers-1.0.0b2.dist-info/namespace_packages.txt
collective.classifiers-1.0.0b2.dist-info/top_level.txt
collective.classifiers-1.0.0b2.dist-info/RECORD
