Metadata-Version: 2.1
Name: collective.classifiers
Version: 1.0.0b2
Summary: Themes and categories behavior
Home-page: http://zestsoftware.nl/
Author: Zest Software
Author-email: info@zestsoftware.nl
License: GPL
Keywords: collective.classifiers theme info class
Platform: UNKNOWN
Classifier: Development Status :: 5 - Production/Stable
Classifier: Framework :: Plone
Classifier: Framework :: Plone :: 5.2
Classifier: Framework :: Plone :: 6.0
Classifier: License :: OSI Approved :: GNU General Public License (GPL)
Classifier: Programming Language :: Python
Classifier: Programming Language :: Python :: 2.7
Classifier: Programming Language :: Python :: 3.6
Classifier: Programming Language :: Python :: 3.7
Classifier: Programming Language :: Python :: 3.8
Classifier: Programming Language :: Python :: 3.9
Requires-Dist: setuptools
Requires-Dist: plone.app.z3cform
Requires-Dist: plone.behavior
Requires-Dist: zope.component
Requires-Dist: zope.interface
Requires-Dist: zope.schema
Provides-Extra: test
Requires-Dist: plone.app.dexterity ; extra == 'test'
Requires-Dist: plone.app.testing ; extra == 'test'
